[{"type":"function","name":"available","constant":true,"stateMutability":"view","payable":false,"inputs":[{"type":"uint256","name":"_tokenId"}],"outputs":[{"type":"bool"}]},{"type":"function","name":"getPrice","constant":true,"stateMutability":"view","payable":false,"inputs":[],"outputs":[{"type":"uint256"}]},{"type":"function","name":"purchase","constant":false,"stateMutability":"payable","payable":true,"inputs":[{"type":"uint256","name":"_tokenId"}],"outputs":[]},{"type":"function","name":"tokens","constant":true,"stateMutability":"view","payable":false,"inputs":[{"type":"uint256"}],"outputs":[{"type":"address"}]}]